LICENCE
README.md
bottle_pymysql.py
setup.py
bottle_pymysql.egg-info/PKG-INFO
bottle_pymysql.egg-info/SOURCES.txt
bottle_pymysql.egg-info/dependency_links.txt
bottle_pymysql.egg-info/requires.txt
bottle_pymysql.egg-info/top_level.txt